apis_acdhch_default_settings/__init__.py
apis_acdhch_default_settings/ldapauth.py
apis_acdhch_default_settings/querysets.py
apis_acdhch_default_settings/settings.py
apis_acdhch_default_settings/urls.py
apis_acdhch_default_settings/views.py
apis_acdhch_default_settings/locale/de/LC_MESSAGES/django.mo
apis_acdhch_default_settings/locale/de/LC_MESSAGES/django.po
apis_acdhch_default_settings/templates/base.html
apis_acdhch_default_settings/templates/e53_place_from_typesense_autocomplete_result.html
apis_acdhch_default_settings/templates/imprint.html
apis_acdhch_default_settings/templates/partials/footer.html
apis_acdhch_default_settings-2.16.0.dist-info/METADATA
apis_acdhch_default_settings-2.16.0.dist-info/WHEEL
apis_acdhch_default_settings-2.16.0.dist-info/licenses/LICENSE
apis_acdhch_default_settings-2.16.0.dist-info/RECORD
