Metadata-Version: 2.4
Name: apis-acdhch-default-settings
Version: 2.16.0
Summary: Default settings for APIS instances at the ACDH-CH
Project-URL: source, https://github.com/acdh-oeaw/apis-acdhch-default-settings
Project-URL: changelog, https://github.com/acdh-oeaw/apis-acdhch-default-settings/blob/main/CHANGELOG.md
Project-URL: issues, https://github.com/acdh-oeaw/apis-acdhch-default-settings/issues
Author-email: Birger Schacht <birger.schacht@oeaw.ac.at>
License-Expression: MIT
License-File: LICENSE
Requires-Python: >=3.13
Requires-Dist: apis-acdhch-django-auditlog>=0.2.1
Requires-Dist: apis-core-rdf>=0.58.0
Requires-Dist: dj-database-url<4.0,>=2.0.0
Requires-Dist: django-allow-cidr<0.9,>=0.6
Requires-Dist: django-auditlog>=3.1.2
Requires-Dist: django-auth-ldap<6.0,>=4.6.0
Requires-Dist: django-csp<4.0,>=3.7
Requires-Dist: django-removals<=2.0,>=1.0.5
Requires-Dist: django>=5
Requires-Dist: opentelemetry-distro
Requires-Dist: opentelemetry-exporter-otlp
Requires-Dist: opentelemetry-instrumentation-asgi
Requires-Dist: opentelemetry-instrumentation-django
Requires-Dist: opentelemetry-instrumentation-logging
Requires-Dist: opentelemetry-instrumentation-psycopg2
Requires-Dist: opentelemetry-instrumentation-wsgi
Requires-Dist: requests>=2
Requires-Dist: whitenoise<7.0,>=5.2
